whl2conda/VERSION
whl2conda/__about__.py
whl2conda/__init__.py
whl2conda/__main__.py
whl2conda/py.typed
whl2conda/settings.py
whl2conda/api/__init__.py
whl2conda/api/converter.py
whl2conda/api/stdrename.json
whl2conda/api/stdrename.py
whl2conda/cli/__init__.py
whl2conda/cli/build.py
whl2conda/cli/common.py
whl2conda/cli/config.py
whl2conda/cli/convert.py
whl2conda/cli/diff.py
whl2conda/cli/install.py
whl2conda/cli/main.py
whl2conda/external/__init__.py
whl2conda/external/version.py
whl2conda/impl/__init__.py
whl2conda/impl/download.py
whl2conda/impl/prompt.py
whl2conda/impl/pyproject.py
whl2conda/impl/wheel.py
whl2conda-25.3.0.dist-info/METADATA
whl2conda-25.3.0.dist-info/WHEEL
whl2conda-25.3.0.dist-info/entry_points.txt
whl2conda-25.3.0.dist-info/licenses/LICENSE.md
whl2conda-25.3.0.dist-info/RECORD
