Metadata-Version: 2.4
Name: whl2conda
Version: 25.3.0
Summary: Build conda packages directly from pure python wheels
Project-URL: homepage, https://github.com/analog-cbarber/whl2conda
Project-URL: repository, https://github.com/analog-cbarber/whl2conda
Project-URL: documentation, https://zuzukin.github.io/whl2conda/
Author-email: Christopher Barber <christopher.barber@analog.com>
License-Expression: Apache-2.0
License-File: LICENSE.md
Keywords: build,conda,wheel
Classifier: Development Status :: 3 - Alpha
Classifier: Intended Audience :: Developers
Classifier: Programming Language :: Python :: 3.8
Classifier: Programming Language :: Python :: 3.9
Classifier: Programming Language :: Python :: 3.10
Classifier: Programming Language :: Python :: 3.11
Classifier: Programming Language :: Python :: 3.12
Classifier: Topic :: Software Development :: Build Tools
Requires-Python: >=3.9
Requires-Dist: conda-package-handling>=2.2
Requires-Dist: platformdirs>=3.10
Requires-Dist: pyyaml>=6.0
Requires-Dist: tomlkit>=0.12
Requires-Dist: wheel>=0.41
